prettipy/__init__.py
prettipy/__main__.py
prettipy/cli.py
prettipy/config.py
prettipy/core.py
prettipy/formatter.py
prettipy/github_handler.py
prettipy/linking.py
prettipy/sorting.py
prettipy/styles.py
prettipy/syntax.py
prettipy/tree.py
prettipy-0.1.5.dist-info/licenses/LICENSE
prettipy-0.1.5.dist-info/METADATA
prettipy-0.1.5.dist-info/WHEEL
prettipy-0.1.5.dist-info/entry_points.txt
prettipy-0.1.5.dist-info/top_level.txt
prettipy-0.1.5.dist-info/RECORD
