Metadata-Version: 2.4
Name: prettipy
Version: 0.1.5
Summary: Convert Python code to beautifully formatted, syntax-highlighted PDFs
Author-email: Your Name <your.email@example.com>
License: MIT
Project-URL: Homepage, https://github.com/yourusername/prettipy
Project-URL: Documentation, https://github.com/yourusername/prettipy#readme
Project-URL: Repository, https://github.com/yourusername/prettipy.git
Project-URL: Bug Tracker, https://github.com/yourusername/prettipy/issues
Keywords: pdf,python,syntax-highlighting,documentation,code-to-pdf
Classifier: Development Status :: 4 - Beta
Classifier: Intended Audience :: Developers
Classifier: License :: OSI Approved :: MIT License
Classifier: Programming Language :: Python :: 3
Classifier: Programming Language :: Python :: 3.8
Classifier: Programming Language :: Python :: 3.9
Classifier: Programming Language :: Python :: 3.10
Classifier: Programming Language :: Python :: 3.11
Classifier: Programming Language :: Python :: 3.12
Classifier: Topic :: Software Development :: Documentation
Classifier: Topic :: Utilities
Requires-Python: >=3.8
License-File: LICENSE
Requires-Dist: reportlab>=4.0.0
Requires-Dist: pygments>=2.15.0
Requires-Dist: networkx>=3.0
Requires-Dist: directory-tree>=1.0.0
Requires-Dist: gitpython>=3.1.0
Provides-Extra: dev
Requires-Dist: pytest>=7.0.0; extra == "dev"
Requires-Dist: pytest-cov>=4.0.0; extra == "dev"
Requires-Dist: black>=23.0.0; extra == "dev"
Requires-Dist: flake8>=6.0.0; extra == "dev"
Requires-Dist: mypy>=1.0.0; extra == "dev"
Requires-Dist: pre-commit>=3.0.0; extra == "dev"
Provides-Extra: rich
Requires-Dist: rich>=13.0.0; extra == "rich"
Dynamic: license-file
